module1/__init__.py
module1/core.py
module1/helpers.py
mymodule1-0.1.0.dist-info/LICENSE
mymodule1-0.1.0.dist-info/METADATA
mymodule1-0.1.0.dist-info/WHEEL
mymodule1-0.1.0.dist-info/top_level.txt
mymodule1-0.1.0.dist-info/RECORD
