Metadata-Version: 2.1
Name: mymodule1
Version: 0.1.0
Summary: UNKNOWN
Home-page: https://github.com/zk4/module
Author: zk4
Author-email: liuzq7@gmail.com
License: Copyright (c) 2017, Kenneth Reitz
